{"id":"f298df3d-29e1-4886-8beb-ed9e9ff49ee2","timestamp":1751857772471,"matcher":{"static":{"/sitemap.xml":{"redirect":"/sitemap_index.xml"},"/__nuxt_content/content_bg/sql_dump.txt":{"prerender":true},"/__nuxt_content/articles_bg/sql_dump.txt":{"prerender":true},"/__nuxt_content/projects_bg/sql_dump.txt":{"prerender":true},"/__nuxt_content/stack/sql_dump.txt":{"prerender":true},"/__nuxt_content/faq_bg/sql_dump.txt":{"prerender":true}},"wildcard":{},"dynamic":{}},"prerendered":["/bg","/","/bg/sitemap.xml","/program"]}